github_bot_api-0.7.0.dist-info/METADATA
github_bot_api-0.7.0.dist-info/WHEEL
github_bot_api-0.7.0.dist-info/entry_points.txt
github_bot_api-0.7.0.dist-info/licenses/LICENSE
github_bot_api/__init__.py
github_bot_api/app.py
github_bot_api/app_test.py
github_bot_api/event.py
github_bot_api/flask.py
github_bot_api/py.typed
github_bot_api/signature.py
github_bot_api/tests/test_import.py
github_bot_api/token.py
github_bot_api/utils/__init__.py
github_bot_api/utils/functions.py
github_bot_api/utils/mime.py
github_bot_api/utils/types.py
github_bot_api/webhook.py
github_bot_api-0.7.0.dist-info/RECORD
