Metadata-Version: 2.1
Name: github-bot-api
Version: 0.7.0
Summary: API for creating GitHub bots and webhooks in Python.
Author-Email: Niklas Rosenstein <rosensteinniklas@gmail.com>
License: MIT
Classifier: Intended Audience :: Developers
Classifier: License :: OSI Approved :: MIT License
Classifier: Programming Language :: Python :: 3
Classifier: Programming Language :: Python :: 3.9
Classifier: Programming Language :: Python :: 3.10
Classifier: Programming Language :: Python :: 3.11
Classifier: Programming Language :: Python :: 3.12
Classifier: Programming Language :: Python :: 3.13
Project-URL: Bug Tracker, https://github.com/NiklasRosenstein/python-github-bot-api/issues
Project-URL: Documentation, https://niklasrosenstein.github.io/python-github-bot-api/
Project-URL: Repository, https://github.com/NiklasRosenstein/python-github-bot-api
Requires-Python: <4.0,>=3.9
Requires-Dist: cryptography<44.0.1,>=44.0.0
Requires-Dist: pygithub>=2.5.0
Requires-Dist: PyJWT<3.0.0,>=2.6.0
Requires-Dist: requests<3.0.0,>=2.28.2
Requires-Dist: urllib3<2.4.0,>=2.3.0
